setup.py
src/signalAlign.egg-info/PKG-INFO
src/signalAlign.egg-info/SOURCES.txt
src/signalAlign.egg-info/dependency_links.txt
src/signalAlign.egg-info/requires.txt
src/signalAlign.egg-info/top_level.txt
src/signalalign/__init__.py
src/signalalign/motif.py
src/signalalign/nanoporeRead.py
src/signalalign/toil/__init__.py
src/signalalign/toil/ledger.py
src/signalalign/toil/signalAlignment.py