Metadata-Version: 1.0
Name: signalAlign
Version: 0.1.2
Summary: A library for signal-level analysis of ONT data
Home-page: https://github.com/ArtRand/signalAlign
Author: Art Rand
Author-email: arand@soe.ucsc.edu
License: UNKNOWN
Platform: UNKNOWN
